neuro_api/__init__.py
neuro_api/_deprecate.py
neuro_api/api.py
neuro_api/client.py
neuro_api/command.py
neuro_api/event.py
neuro_api/json_schema_types.py
neuro_api/py.typed
neuro_api/server.py
neuro_api/trio_ws.py
neuro_api-3.1.1.dist-info/licenses/LICENSE
neuro_api-3.1.1.dist-info/METADATA
neuro_api-3.1.1.dist-info/WHEEL
neuro_api-3.1.1.dist-info/top_level.txt
neuro_api-3.1.1.dist-info/RECORD
