Metadata-Version: 2.4
Name: neuro_api
Version: 3.1.1
Summary: Neuro-API SDK for Python
Author-email: CoolCat467 <CoolCat467@duck.com>
License:                    GNU LESSER GENERAL PUBLIC LICENSE
Project-URL: Source, https://github.com/CoolCat467/Neuro-API
Project-URL: Bug Tracker, https://github.com/CoolCat467/Neuro-API/issues
Keywords: neuro-api,sdk
Classifier: Development Status :: 4 - Beta
Classifier: Intended Audience :: End Users/Desktop
Classifier: License :: OSI Approved :: GNU Lesser General Public License v3 (LGPLv3)
Classifier: Natural Language :: English
Classifier: Programming Language :: Python :: 3
Classifier: Programming Language :: Python :: 3.10
Classifier: Programming Language :: Python :: 3.11
Classifier: Programming Language :: Python :: 3.12
Classifier: Programming Language :: Python :: 3.13
Classifier: Programming Language :: Python :: 3.14
Classifier: Programming Language :: Python :: 3 :: Only
Classifier: Topic :: Games/Entertainment
Classifier: Topic :: Games/Entertainment :: Board Games
Classifier: Topic :: Games/Entertainment :: Turn Based Strategy
Classifier: Topic :: Internet
Classifier: Topic :: Software Development :: Libraries :: pygame
Classifier: Operating System :: OS Independent
Classifier: Framework :: Trio
Classifier: Typing :: Typed
Requires-Python: >=3.10
License-File: LICENSE
Requires-Dist: trio-websocket~=0.12.2
Requires-Dist: orjson<4,>=3.10
Requires-Dist: trio>=0.32.0
Requires-Dist: exceptiongroup>=1.2.2
Requires-Dist: libcomponent~=0.0.5
Requires-Dist: typing_extensions>=4.12.2
Provides-Extra: tests
Requires-Dist: pytest>=5.0; extra == "tests"
Requires-Dist: pytest-cov>=6.0.0; extra == "tests"
Requires-Dist: pytest-trio>=0.8.0; extra == "tests"
Requires-Dist: coverage>=7.2.5; extra == "tests"
Requires-Dist: uv>=0.5.21; extra == "tests"
Provides-Extra: tools
Requires-Dist: ruff>=0.9.2; extra == "tools"
Requires-Dist: pre-commit>=4.2.0; extra == "tools"
Requires-Dist: attrs>=25.3.0; extra == "tools"
Requires-Dist: mypy>=1.19.0; extra == "tools"
Dynamic: license-file
